pj/__init__.py
pj/__main__.py
pj/pj.py
pj_cli-0.1.0.dist-info/WHEEL
pj_cli-0.1.0.dist-info/entry_points.txt
pj_cli-0.1.0.dist-info/METADATA
pj_cli-0.1.0.dist-info/RECORD
