Metadata-Version: 2.4
Name: pj-cli
Version: 0.1.0
Summary: pj is a CLI tool.
Keywords: cli,ai
Author: Mahadi Xion
Author-email: Mahadi Xion <mhxions@gmail.com>
License-Expression: AGPL-3.0-only
Requires-Dist: rich>=14.1.0,<14.2.0
Maintainer: Mahadi Xion
Maintainer-email: Mahadi Xion <mhxions@gmail.com>
Requires-Python: >=3.11, <4
